{
  "hash": "8f691e93",
  "configHash": "449df01c",
  "lockfileHash": "919e291b",
  "browserHash": "79a63334",
  "optimized": {
    "vue": {
      "src": "../../../../node_modules/.pnpm/vue@3.5.13/node_modules/vue/dist/vue.runtime.esm-bundler.js",
      "file": "vue.js",
      "fileHash": "71c4c5c1",
      "needsInterop": false
    },
    "vitepress > @vue/devtools-api": {
      "src": "../../../../node_modules/.pnpm/@vue+devtools-api@7.7.2/node_modules/@vue/devtools-api/dist/index.js",
      "file": "vitepress___@vue_devtools-api.js",
      "fileHash": "20b79365",
      "needsInterop": false
    },
    "vitepress > @vueuse/core": {
      "src": "../../../../node_modules/.pnpm/@vueuse+core@12.8.2/node_modules/@vueuse/core/index.mjs",
      "file": "vitepress___@vueuse_core.js",
      "fileHash": "b60040eb",
      "needsInterop": false
    },
    "@theme/index": {
      "src": "../../../../node_modules/.pnpm/vitepress@1.6.3_@algolia+client-search@5.23.0_postcss@8.5.3_search-insights@2.17.3/node_modules/vitepress/dist/client/theme-default/index.js",
      "file": "@theme_index.js",
      "fileHash": "834edbb1",
      "needsInterop": false
    }
  },
  "chunks": {
    "chunk-6ODFCPKZ": {
      "file": "chunk-6ODFCPKZ.js"
    },
    "chunk-JN5NFW2R": {
      "file": "chunk-JN5NFW2R.js"
    }
  }
}